Ionburst/__init__.py
Ionburst/apiHandler.py
Ionburst/ionburst.py
Ionburst/objdict.py
Ionburst/settings.py
ionburst_sdk_python-1.1.1.dist-info/DESCRIPTION.rst
ionburst_sdk_python-1.1.1.dist-info/METADATA
ionburst_sdk_python-1.1.1.dist-info/RECORD
ionburst_sdk_python-1.1.1.dist-info/WHEEL
ionburst_sdk_python-1.1.1.dist-info/metadata.json
ionburst_sdk_python-1.1.1.dist-info/top_level.txt
