Metadata-Version: 2.0
Name: ionburst-sdk-python
Version: 1.1.1
Summary: Ionburst SDK for Python
Home-page: https://gitlab.com/ionburst/ionburst-sdk-python/
Author: Ionburst Limited
Author-email: sdk@ionburst.io
License: Apache-2.0
Platform: UNKNOWN
Classifier: Programming Language :: Python :: 3
License-File: LICENSE
Requires-Dist: certifi (==2020.4.5.1)
Requires-Dist: chardet (>=3.0.4)
Requires-Dist: idna (>=2.9)
Requires-Dist: python-dotenv (>=0.13.0)
Requires-Dist: requests (>=2.23.0)
Requires-Dist: urllib3 (>=1.25.9)
